{
	"name": "ETLOrchestration",
	"properties": {
		"activities": [
			{
				"name": "s_Import_Control",
				"type": "SqlServerStoredProcedure",
				"policy": {
					"timeout": "7.00:00:00",
					"retry": 0,
					"retryIntervalInSeconds": 30,
					"secureOutput": false,
					"secureInput": false
				},
				"typeProperties": {
					"storedProcedureName": "[Insight].[s_Import_Control]",
					"storedProcedureParameters": {
						"PathName": {
							"value": "blobs",
							"type": "string"
						},
						"TableName": {
							"value": "All",
							"type": "string"
						},
						"ReCreateTables": {
							"value": "0",
							"type": "bool"
						},
						"TableType": {
							"value": "regular",
							"type": "string"
						},
						"SystemTablesExist": {
							"value": "0",
							"type": "int"
						}
					}
				},
				"linkedServiceName": {
					"referenceName": "AzureSqlDbLinkedService",
					"type": "LinkedServiceReference"
				}
			}
		]
	}
}